MANIFEST.in
README.md
requirements.txt
setup.py
test_requirements.txt
version.txt
cloudshell/__init__.py
cloudshell/layer_one/__init__.py
cloudshell/layer_one/migration_tool/__init__.py
cloudshell/layer_one/migration_tool/__main__.py
cloudshell/layer_one/migration_tool/bootstrap.py
cloudshell/layer_one/migration_tool/commands/__init__.py
cloudshell/layer_one/migration_tool/commands/config_commands.py
cloudshell/layer_one/migration_tool/commands/migration_commands.py
cloudshell/layer_one/migration_tool/commands/resources_commands.py
cloudshell/layer_one/migration_tool/entities/__init__.py
cloudshell/layer_one/migration_tool/entities/config_unit.py
cloudshell/layer_one/migration_tool/entities/connection.py
cloudshell/layer_one/migration_tool/entities/logical_route.py
cloudshell/layer_one/migration_tool/entities/migration_config.py
cloudshell/layer_one/migration_tool/entities/migration_operation.py
cloudshell/layer_one/migration_tool/entities/port.py
cloudshell/layer_one/migration_tool/entities/resource.py
cloudshell/layer_one/migration_tool/handlers/__init__.py
cloudshell/layer_one/migration_tool/handlers/logical_routes_handler.py
cloudshell/layer_one/migration_tool/handlers/migration_config_handler.py
cloudshell/layer_one/migration_tool/handlers/migration_config_parser.py
cloudshell/layer_one/migration_tool/handlers/migration_operation_handler.py
cloudshell/layer_one/migration_tool/helpers/__init__.py
cloudshell/layer_one/migration_tool/helpers/config_helper.py
cloudshell/layer_one/migration_tool/helpers/connection_associator.py
cloudshell/layer_one/migration_tool/helpers/connection_helper.py
cloudshell/layer_one/migration_tool/helpers/logger.py
cloudshell/layer_one/migration_tool/helpers/logical_route_helper.py
cloudshell/layer_one/migration_tool/helpers/output_formater.py
cloudshell/layer_one/migration_tool/helpers/resource_operation_helper.py
cloudshell/layer_one/migration_tool/validators/__init__.py
cloudshell_l1_migration.egg-info/PKG-INFO
cloudshell_l1_migration.egg-info/SOURCES.txt
cloudshell_l1_migration.egg-info/dependency_links.txt
cloudshell_l1_migration.egg-info/entry_points.txt
cloudshell_l1_migration.egg-info/not-zip-safe
cloudshell_l1_migration.egg-info/requires.txt
cloudshell_l1_migration.egg-info/top_level.txt