Metadata-Version: 1.1
Name: cloudshell-l1-migration
Version: 1.0.5
Summary: QualiSystems CloudShell L1 migration script
Home-page: https://github.com/QualiSystems/Cloudshell-L1-Migration
Author: QualiSystems
Author-email: info@qualisystems.com
License: Apache Software License 2.0
Keywords: migration cloudshell quali command-line cli
Platform: UNKNOWN
Classifier: Development Status :: 5 - Production/Stable
Classifier: Programming Language :: Python :: 2.7
Classifier: Topic :: Software Development :: Libraries
Classifier: License :: OSI Approved :: Apache Software License
